tests/__init__.py
tests/bools_test.py
tests/dates_test.py
tests/enum_test.py
tests/lists_test.py
tests/math_test.py
tests/objects_test.py
tests/dicts/__init__.py
tests/dicts/chained_dict_test.py
tests/dicts/helpers_test.py
tests/dicts/limited_dict_test.py
utils/__init__.py
utils/bools.py
utils/dates.py
utils/enum.py
utils/lists.py
utils/math.py
utils/objects.py
utils/dicts/__init__.py
utils/dicts/chained_dict.py
utils/dicts/helpers.py
utils/dicts/limited_dict.py
utils-0.9.0.dist-info/DESCRIPTION.rst
utils-0.9.0.dist-info/LICENSE.txt
utils-0.9.0.dist-info/METADATA
utils-0.9.0.dist-info/RECORD
utils-0.9.0.dist-info/WHEEL
utils-0.9.0.dist-info/metadata.json
utils-0.9.0.dist-info/top_level.txt
