Metadata-Version: 1.0
Name: utils
Version: 0.9.0
Summary: Python Distribution Utilities
Home-page: http://github.com/haaksmash/pyutils
Author: Haak Saxberg
Author-email: haak.erling@gmail.com
License: UNKNOWN
Platform: UNKNOWN
